planning_library/__init__.py
planning_library/action_executors/__init__.py
planning_library/action_executors/base_action_executor.py
planning_library/action_executors/default_action_executor.py
planning_library/action_executors/meta_tools.py
planning_library/components/__init__.py
planning_library/components/agent_component.py
planning_library/components/base_component.py
planning_library/components/evaluation/__init__.py
planning_library/components/evaluation/evaluator_component.py
planning_library/components/evaluation/threshold_judge.py
planning_library/components/runnable_component.py
planning_library/function_calling_parsers/__init__.py
planning_library/function_calling_parsers/base_parser.py
planning_library/function_calling_parsers/openai_functions_parser.py
planning_library/function_calling_parsers/openai_tools_parser.py
planning_library/function_calling_parsers/parser_registry.py
planning_library/primitives/__init__.py
planning_library/primitives/output_parsers/__init__.py
planning_library/primitives/output_parsers/evaluation_output_parser.py
planning_library/py.typed
planning_library/strategies/__init__.py
planning_library/strategies/adapt/__init__.py
planning_library/strategies/adapt/adapt_strategy.py
planning_library/strategies/adapt/components/__init__.py
planning_library/strategies/adapt/components/executor.py
planning_library/strategies/adapt/components/planner.py
planning_library/strategies/adapt/utils/__init__.py
planning_library/strategies/adapt/utils/planner_output_parser.py
planning_library/strategies/adapt/utils/typing_utils.py
planning_library/strategies/base_strategy.py
planning_library/strategies/reflexion/__init__.py
planning_library/strategies/reflexion/components/__init__.py
planning_library/strategies/reflexion/components/actor.py
planning_library/strategies/reflexion/components/evaluator.py
planning_library/strategies/reflexion/components/self_reflection.py
planning_library/strategies/reflexion/reflexion_graph.py
planning_library-0.1.4.dist-info/LICENSE
planning_library-0.1.4.dist-info/METADATA
planning_library-0.1.4.dist-info/WHEEL
planning_library-0.1.4.dist-info/RECORD
