Metadata-Version: 2.1
Name: planning-library
Version: 0.1.4
Summary: LangChain-based library with planning algorithms for AI Agents.
License: MIT
Author: Alexandra Eliseeva
Author-email: alexandra.eliseeva@jetbrains.com
Requires-Python: >=3.9,<4.0
Classifier: License :: OSI Approved :: MIT License
Classifier: Programming Language :: Python :: 3
Classifier: Programming Language :: Python :: 3.9
Classifier: Programming Language :: Python :: 3.10
Classifier: Programming Language :: Python :: 3.11
Classifier: Programming Language :: Python :: 3.12
Requires-Dist: gymnasium (>=0.29.1,<0.30.0)
Requires-Dist: langchain (>=0.1.4,<0.2.0)
Requires-Dist: langchain-core (>=0.1.30,<0.2.0)
Requires-Dist: langgraph (>=0.0.26,<0.0.27)
Requires-Dist: urllib3 (<1.27)
